porrametict-first-package/__init__.py
porrametict-first-package/module.py
porrametict_first_package/__init__.py
porrametict_first_package/module.py
porrametict_first_package-0.3.0.dist-info/METADATA
porrametict_first_package-0.3.0.dist-info/WHEEL
porrametict_first_package-0.3.0.dist-info/top_level.txt
porrametict_first_package-0.3.0.dist-info/RECORD
