Metadata-Version: 2.1
Name: porrametict-first-package
Version: 0.3.0
Summary: My first package
Home-page: https://github.com/porrametict
Author: Poramet Tangon
Author-email: porrametict@gmail.com
License: UNKNOWN
Platform: UNKNOWN
Classifier: Development Status :: 3 - Alpha
Classifier: License :: OSI Approved :: MIT License
Classifier: Programming Language :: Python :: 3
Requires-Dist: numpy
Requires-Dist: requests
